tailgrid/__init__.py
tailgrid/__main__.py
tailgrid-0.6.0.dist-info/licenses/LICENSE
tailgrid-0.6.0.dist-info/licenses/NOTICE
tailgrid-0.6.0.dist-info/METADATA
tailgrid-0.6.0.dist-info/WHEEL
tailgrid-0.6.0.dist-info/entry_points.txt
tailgrid-0.6.0.dist-info/top_level.txt
tailgrid-0.6.0.dist-info/RECORD
