Metadata-Version: 2.4
Name: tailgrid
Version: 0.6.0
Summary: Multi-tile tail viewer for terminal
Author: Fabio Ferreira
License-Expression: Apache-2.0
Keywords: tail,terminal,curses,log,viewer,grid
Classifier: Environment :: Console :: Curses
Classifier: Operating System :: POSIX
Classifier: Programming Language :: Python :: 3.10
Classifier: Programming Language :: Python :: 3.11
Classifier: Programming Language :: Python :: 3.12
Classifier: Programming Language :: Python :: 3.13
Requires-Python: >=3.10
License-File: LICENSE
License-File: NOTICE
Provides-Extra: dev
Requires-Dist: pytest>=7.0; extra == "dev"
Dynamic: license-file
